odoo8_addon_web_search_autocomplete_prefetch-8.0.1.0.0.99.dev14-py2.7-nspkg.pth
odoo8_addon_web_search_autocomplete_prefetch-8.0.1.0.0.99.dev14.dist-info/DESCRIPTION.rst
odoo8_addon_web_search_autocomplete_prefetch-8.0.1.0.0.99.dev14.dist-info/METADATA
odoo8_addon_web_search_autocomplete_prefetch-8.0.1.0.0.99.dev14.dist-info/RECORD
odoo8_addon_web_search_autocomplete_prefetch-8.0.1.0.0.99.dev14.dist-info/WHEEL
odoo8_addon_web_search_autocomplete_prefetch-8.0.1.0.0.99.dev14.dist-info/metadata.json
odoo8_addon_web_search_autocomplete_prefetch-8.0.1.0.0.99.dev14.dist-info/namespace_packages.txt
odoo8_addon_web_search_autocomplete_prefetch-8.0.1.0.0.99.dev14.dist-info/top_level.txt
odoo_addons/web_search_autocomplete_prefetch/README.rst
odoo_addons/web_search_autocomplete_prefetch/__init__.py
odoo_addons/web_search_autocomplete_prefetch/__openerp__.py
odoo_addons/web_search_autocomplete_prefetch/i18n/es.po
odoo_addons/web_search_autocomplete_prefetch/i18n/fi.po
odoo_addons/web_search_autocomplete_prefetch/i18n/sl.po
odoo_addons/web_search_autocomplete_prefetch/i18n/tr.po
odoo_addons/web_search_autocomplete_prefetch/i18n/web_search_autocomplete_prefetch.pot
odoo_addons/web_search_autocomplete_prefetch/images/web_search_autocomplete_prefetch.png
odoo_addons/web_search_autocomplete_prefetch/static/description/icon.png
odoo_addons/web_search_autocomplete_prefetch/static/src/js/web_search_autocomplete_prefetch.js
odoo_addons/web_search_autocomplete_prefetch/views/base_view.xml
odoo_addons/web_search_autocomplete_prefetch/views/templates.xml
